tracking_decorator/__init__.py
tracking_decorator/track_changes.py
tracking_decorator/trash_collections.py
tracking_decorator-0.0.4.dist-info/METADATA
tracking_decorator-0.0.4.dist-info/WHEEL
tracking_decorator-0.0.4.dist-info/licenses/LICENSE
tracking_decorator-0.0.4.dist-info/RECORD
