Metadata-Version: 2.3
Name: tracking_decorator
Version: 0.0.4
Summary: A small decorator for tracking changed attributes in a class
Project-URL: Homepage, https://github.com/pypa/sampleproject
Project-URL: Issues, https://github.com/pypa/sampleproject/issues
Author-email: Ian Lavine <ian.lavine@mail.utoronto.ca>
License-File: LICENSE
Classifier: License :: OSI Approved :: MIT License
Classifier: Operating System :: OS Independent
Classifier: Programming Language :: Python :: 3
Requires-Python: >=3.8
